mqt/qecc/ecc_qiskit_wrapper.py
mqt/qecc/_version.py
mqt/qecc/pyqecc.cpython-312-aarch64-linux-gnu.so
mqt/qecc/py.typed
mqt/qecc/_version.pyi
mqt/qecc/__init__.py
mqt/qecc/pyqecc.pyi
mqt/qecc/codes/css_code.py
mqt/qecc/codes/constructions.py
mqt/qecc/codes/pauli.py
mqt/qecc/codes/stabilizer_code.py
mqt/qecc/codes/concatenation.py
mqt/qecc/codes/square_octagon_color_code.py
mqt/qecc/codes/color_code.py
mqt/qecc/codes/symplectic.py
mqt/qecc/codes/bb_codes.py
mqt/qecc/codes/__init__.py
mqt/qecc/codes/hexagonal_color_code.py
mqt/qecc/codes/carbon/hz.npy
mqt/qecc/codes/carbon/hx.npy
mqt/qecc/codes/golay/hz.npy
mqt/qecc/codes/golay/hx.npy
mqt/qecc/codes/rotated_surface_d3/hz.npy
mqt/qecc/codes/rotated_surface_d3/hx.npy
mqt/qecc/codes/steane/hz.npy
mqt/qecc/codes/steane/hx.npy
mqt/qecc/codes/hamming_15/hz.npy
mqt/qecc/codes/hamming_15/hx.npy
mqt/qecc/codes/cc_4_8_8_d5/hz.npy
mqt/qecc/codes/cc_4_8_8_d5/hx.npy
mqt/qecc/codes/shor/hz.npy
mqt/qecc/codes/shor/hx.npy
mqt/qecc/codes/tetrahedral/hz.npy
mqt/qecc/codes/tetrahedral/hx.npy
mqt/qecc/codes/rotated_surface_d5/hz.npy
mqt/qecc/codes/rotated_surface_d5/hx.npy
mqt/qecc/circuit_synthesis/circuit_utils.py
mqt/qecc/circuit_synthesis/simulation_det.py
mqt/qecc/circuit_synthesis/state_prep_det.py
mqt/qecc/circuit_synthesis/simulation.py
mqt/qecc/circuit_synthesis/encoding.py
mqt/qecc/circuit_synthesis/state_prep.py
mqt/qecc/circuit_synthesis/__init__.py
mqt/qecc/circuit_synthesis/synthesis_utils.py
mqt/qecc/circuit_synthesis/encoding_circuits/hamming.qasm
mqt/qecc/circuit_synthesis/encoding_circuits/6_2_2.qasm
mqt/qecc/circuit_synthesis/encoding_circuits/shor.qasm
mqt/qecc/circuit_synthesis/encoding_circuits/10_1_2.qasm
mqt/qecc/circuit_synthesis/encoding_circuits/carbon.qasm
mqt/qecc/circuit_synthesis/encoding_circuits/4_2_2.qasm
mqt/qecc/circuit_synthesis/encoding_circuits/steane.qasm
mqt/qecc/circuit_synthesis/encoding_circuits/surface.qasm
mqt_qecc-1.9.0.dist-info/WHEEL
mqt_qecc-1.9.0.dist-info/RECORD
mqt_qecc-1.9.0.dist-info/entry_points.txt
mqt_qecc-1.9.0.dist-info/METADATA
mqt_qecc-1.9.0.dist-info/licenses/LICENSE
