Metadata-Version: 2.1
Name: mqt.qecc
Version: 1.9.0
Summary: QECC - An MQT Tool for Quantum Error Correcting Codes
Keywords: MQT,quantum-computing,error-correction,MaxSAT,QLDPC
Author-Email: Lucas Berent <lucas.berent@tum.de>, Lukas Burgholzer <lukas.burgholzer@tum.de>, "Peter-Jan H.S. Derks" <peter-janderks@hotmail.com>, Timo Hillmann <timo.hillmann@rwth-aachen.de>, Tom Peham <tom.peham@tum.de>, Ludwig Schmid <ludwig.s.schmid@tum.de>
License: MIT License
Classifier: Topic :: Scientific/Engineering :: Electronic Design Automation (EDA)
Classifier: Intended Audience :: Science/Research
Classifier: Natural Language :: English
Classifier: Operating System :: POSIX :: Linux
Classifier: Operating System :: MacOS
Classifier: Operating System :: Microsoft :: Windows
Classifier: License :: OSI Approved :: MIT License
Classifier: Programming Language :: C++
Classifier: Programming Language :: Python
Classifier: Programming Language :: Python :: 3
Classifier: Programming Language :: Python :: 3 :: Only
Classifier: Programming Language :: Python :: 3.9
Classifier: Programming Language :: Python :: 3.10
Classifier: Programming Language :: Python :: 3.11
Classifier: Programming Language :: Python :: 3.12
Classifier: Programming Language :: Python :: 3.13
Classifier: Development Status :: 5 - Production/Stable
Classifier: Typing :: Typed
Project-URL: Homepage, https://github.com/cda-tum/mqt-qecc
Project-URL: Documentation, https://mqt.readthedocs.io/projects/qecc
Project-URL: Issues, https://github.com/cda-tum/mqt-qecc/issues
Project-URL: Discussions, https://github.com/cda-tum/mqt-qecc/discussions
Requires-Python: >=3.9
Requires-Dist: z3-solver>=4.12
Requires-Dist: qecsim
Requires-Dist: ldpc<2,>=0.1.53
Requires-Dist: numpy>=1.26; python_version > "3.11"
Requires-Dist: numpy>=1.24; python_version <= "3.11"
Requires-Dist: qiskit[qasm3-import]>=1.0.0
Requires-Dist: qiskit-aer>=0.15.0
Requires-Dist: stim>=1.13.0
Requires-Dist: multiprocess>=0.70.16
Requires-Dist: bposd>=1.6
Requires-Dist: numba>=0.59; python_version > "3.11"
Requires-Dist: numba>=0.57; python_version <= "3.11"
Requires-Dist: pymatching>=2.2.1
Requires-Dist: qsample>=0.0.2
Requires-Dist: urllib3>=1.26.20
Requires-Dist: fastcore>=1.7.10
Provides-Extra: test
Requires-Dist: pytest>=7.2; extra == "test"
Requires-Dist: pytest-console-scripts>=1.4; extra == "test"
Requires-Dist: pytest-mock>=3.7; extra == "test"
Provides-Extra: coverage
Requires-Dist: mqt.qecc[test]; extra == "coverage"
Requires-Dist: pytest-cov>=4; extra == "coverage"
Provides-Extra: docs
Requires-Dist: furo>=2023.9.10; extra == "docs"
Requires-Dist: setuptools-scm>=8.1; extra == "docs"
Requires-Dist: sphinxcontrib-bibtex>=2.4.2; extra == "docs"
Requires-Dist: sphinx-copybutton>=0.5; extra == "docs"
Requires-Dist: ipykernel; extra == "docs"
Requires-Dist: nbsphinx; extra == "docs"
Requires-Dist: sphinxext-opengraph>=0.9; extra == "docs"
Requires-Dist: sphinx-autodoc-typehints; extra == "docs"
Requires-Dist: qiskit[visualization]; extra == "docs"
Provides-Extra: visualization
Requires-Dist: matplotlib; extra == "visualization"
Requires-Dist: scipy; extra == "visualization"
Provides-Extra: dev
Requires-Dist: mqt.qecc[coverage,docs,visualization]; extra == "dev"
